itkwasm_downsample/__init__.py
itkwasm_downsample/_version.py
itkwasm_downsample/downsample.py
itkwasm_downsample/downsample_async.py
itkwasm_downsample/downsample_bin_shrink.py
itkwasm_downsample/downsample_bin_shrink_async.py
itkwasm_downsample/downsample_label_image.py
itkwasm_downsample/downsample_label_image_async.py
itkwasm_downsample/downsample_sigma.py
itkwasm_downsample/downsample_sigma_async.py
itkwasm_downsample/gaussian_kernel_radius.py
itkwasm_downsample/gaussian_kernel_radius_async.py
itkwasm_downsample-1.8.1.dist-info/METADATA
itkwasm_downsample-1.8.1.dist-info/WHEEL
itkwasm_downsample-1.8.1.dist-info/RECORD
