Metadata-Version: 2.3
Name: itkwasm-downsample
Version: 1.8.1
Summary: Pipelines for downsampling images.
Project-URL: Home, https://github.com/InsightSoftwareConsortium/ITK-Wasm
Project-URL: Source, https://github.com/InsightSoftwareConsortium/ITK-Wasm
Keywords: emscripten,itkwasm,wasi,webassembly
Classifier: Development Status :: 4 - Beta
Classifier: Environment :: WebAssembly
Classifier: Environment :: WebAssembly :: Emscripten
Classifier: Environment :: WebAssembly :: WASI
Classifier: Intended Audience :: Developers
Classifier: Intended Audience :: Science/Research
Classifier: License :: OSI Approved :: Apache Software License
Classifier: Programming Language :: C++
Classifier: Programming Language :: Python
Classifier: Programming Language :: Python :: 3
Classifier: Programming Language :: Python :: 3.8
Classifier: Programming Language :: Python :: 3.9
Classifier: Programming Language :: Python :: 3.10
Classifier: Programming Language :: Python :: 3.11
Classifier: Programming Language :: Python :: 3.12
Requires-Python: >=3.8
Requires-Dist: itkwasm-downsample-emscripten; sys_platform == 'emscripten'
Requires-Dist: itkwasm-downsample-wasi; sys_platform != 'emscripten'
Requires-Dist: itkwasm>=1.0.b145
